README.rst
setup.py
simplestreamer/__init__.py
simplestreamer/simple_streamer.py
simplestreamer/version.py
simplestreamer.egg-info/PKG-INFO
simplestreamer.egg-info/SOURCES.txt
simplestreamer.egg-info/dependency_links.txt
simplestreamer.egg-info/top_level.txt