Metadata-Version: 1.0
Name: simplestreamer
Version: 2016.0.3
Summary: A tiny peer-to-peer data-streaming library
Home-page: https://github.com/computer-whisperer/simplestreamer
Author: Christian Balcom
Author-email: robot.inventor@gmail.com
License: UNKNOWN
Keywords: networking
Platform: UNKNOWN
